p1monitor/__init__.py
p1monitor/exceptions.py
p1monitor/models.py
p1monitor/p1monitor.py
p1monitor/py.typed
p1monitor-3.2.0.dist-info/METADATA
p1monitor-3.2.0.dist-info/WHEEL
p1monitor-3.2.0.dist-info/licenses/LICENSE
p1monitor-3.2.0.dist-info/RECORD
