Metadata-Version: 2.4
Name: p1monitor
Version: 3.2.0
Summary: Asynchronous Python client for the P1 Monitor
License-Expression: MIT
License-File: LICENSE
Keywords: p1,monitor,power,energy,api,async,client
Author: Klaas Schoute
Author-email: <hello@student-techlife.com>
Maintainer: Klaas Schoute
Maintainer-email: <hello@student-techlife.com>
Requires-Python: >=3.11
Classifier: Development Status :: 5 - Production/Stable
Classifier: Framework :: AsyncIO
Classifier: Intended Audience :: Developers
Classifier: License :: OSI Approved :: MIT License
Classifier: Natural Language :: English
Classifier: Programming Language :: Python :: 3.11
Classifier: Programming Language :: Python :: 3.12
Classifier: Programming Language :: Python :: 3.13
Classifier: Programming Language :: Python :: 3
Classifier: Topic :: Software Development :: Libraries :: Python Modules
Requires-Dist: aiohttp (>=3.0.0)
Requires-Dist: yarl (>=1.6.0)
Project-URL: Bug Tracker, https://github.com/klaasnicolaas/python-p1monitor/issues
Project-URL: Changelog, https://github.com/klaasnicolaas/python-p1monitor/releases
Project-URL: Documentation, https://github.com/klaasnicolaas/python-p1monitor
Project-URL: Homepage, https://github.com/klaasnicolaas/python-p1monitor
Project-URL: Repository, https://github.com/klaasnicolaas/python-p1monitor
